README.md
setup.py
pyscc/__init__.py
pyscc/component.py
pyscc/controller.py
pyscc/element.py
pyscc/resource.py
pyscc/service.py
pyscc.egg-info/PKG-INFO
pyscc.egg-info/SOURCES.txt
pyscc.egg-info/dependency_links.txt
pyscc.egg-info/requires.txt
pyscc.egg-info/top_level.txt