Metadata-Version: 1.1
Name: pyscc
Version: 0.2.2
Summary: py-component-controller is an opinionated framework for structuring selenium test suites. This project depends on the pyselenium-js project.
Home-page: https://neetjn.github.io/py-component-controller/
Author: John Nolette
Author-email: john@neetgroup.net
License: Apache2
Platform: UNKNOWN
Classifier: Development Status :: 4 - Beta
Classifier: Intended Audience :: Developers
Classifier: License :: OSI Approved :: Apache Software License
Classifier: Programming Language :: Python :: 2.7
Classifier: Programming Language :: Python :: 3.6
